shekel_mcp/__init__.py
shekel_mcp/__main__.py
shekel_mcp/cli.py
shekel_mcp/client.py
shekel_mcp/tools.py
shekel_mcp-0.1.1.dist-info/METADATA
shekel_mcp-0.1.1.dist-info/WHEEL
shekel_mcp-0.1.1.dist-info/entry_points.txt
shekel_mcp-0.1.1.dist-info/RECORD
