Metadata-Version: 2.4
Name: shekel-mcp
Version: 0.1.1
Summary: MCP server for Shekel Mobility vehicle estimation APIs
Project-URL: Homepage, https://shekelmobility.com
Project-URL: Documentation, https://github.com/shekelmobility/shekel-mcp
Project-URL: Repository, https://github.com/shekelmobility/shekel-mcp
Author-email: Shekel Mobility <support@shekelmobility.com>
License-Expression: MIT
Keywords: ai,api,claude,estimation,mcp,vehicle
Classifier: Development Status :: 4 - Beta
Classifier: Intended Audience :: Developers
Classifier: License :: OSI Approved :: MIT License
Classifier: Programming Language :: Python :: 3
Classifier: Programming Language :: Python :: 3.10
Classifier: Programming Language :: Python :: 3.11
Classifier: Programming Language :: Python :: 3.12
Requires-Python: >=3.10
Requires-Dist: httpx>=0.27.1
Requires-Dist: mcp>=1.2.0
